magichttp/__init__.py
magichttp/_version.py
magichttp/constants.py
magichttp/h1impl/__init__.py
magichttp/h1impl/composers.py
magichttp/h1impl/impls.py
magichttp/h1impl/parsers.py
magichttp/h1impl/py.typed
magichttp/h1impl/stream_mgrs.py
magichttp/initials.py
magichttp/protocols.py
magichttp/py.typed
magichttp/readers.py
magichttp/writers.py
magichttp-1.1.2.dist-info/LICENSE
magichttp-1.1.2.dist-info/WHEEL
magichttp-1.1.2.dist-info/METADATA
magichttp-1.1.2.dist-info/RECORD
